write_type_animations/__init__.py
write_type_animations-0.1.dist-info/LICENCE.txt
write_type_animations-0.1.dist-info/METADATA
write_type_animations-0.1.dist-info/WHEEL
write_type_animations-0.1.dist-info/top_level.txt
write_type_animations-0.1.dist-info/RECORD
