Metadata-Version: 2.1
Name: write-type-animations
Version: 0.1
Summary: This is a simple animation library for cmdline and for real typing animations.
Author: Abdullah Masshood
Author-email: fouziaqateel@gmail.com
Classifier: Programming Language :: Python :: 3
Classifier: License :: OSI Approved :: MIT License
Classifier: Operating System :: OS Independent
License-File: LICENCE.txt
